{
    "contacts": [
        {
            "id": "00000000001",
            "name": "Marcos Otake",
            "email": "marcosotake@gmail.com"
        },
        {
            "id": "00000000002",
            "name": "Marcos Otake2",
            "email": "marcosotake2@gmail.com"
        },
        {
            "id": "00000000003",
            "name": "Marcos Otake3",
            "email": "marcosotake3@gmail.com"
        },
        {
            "id": "00000000004",
            "name": "Marcos Otake4",
            "email": "marcosotake4@gmail.com"
        }        
    ]
}
